{"bakerName":"Dash Master","bakerAccount":"tz1Lc87p6zRaDwzJs9kHvdpm7XzeWE8QTwVB","signupRequired":"false","country":"Germany","website":"https://dashmaster.io","bakerDescription":"Our bakery is the best, and here are any extra details we think everyone should know in 280 characters or less.","nonStandardPaymentDescription":"","upcomingPaymentModelDescription":"","branding":{"logo256":"https://api.baking-bad.org/logos/dashmaster.png","logo1024":"","logoSvg":""},"support":{"email":"","supportUrl":"https://t.me/Dashmaster"},"projects":[],"social":{"telegram":"https://t.me/Dashmaster"},"team":[]}